emus/__init__.py
emus/_defaults.py
emus/autocorrelation.py
emus/avar.py
emus/emus.py
emus/linalg.py
emus/usutils.py
emus-0.9.4.data/scripts/wemus.py
emus-0.9.4.dist-info/METADATA
emus-0.9.4.dist-info/RECORD
emus-0.9.4.dist-info/WHEEL
emus-0.9.4.dist-info/top_level.txt
