Metadata-Version: 2.1
Name: emus
Version: 0.9.4
Summary: Tools and Methods associated with the Eigenvector Method for Umbrella Sampling (EMUS)
Home-page: https://github.com/ehthiede/EMUS
Author: Erik Henning Thiede
Author-email: UNKNOWN
License: LGPL
Platform: UNKNOWN
Classifier: Development Status :: 4 - Beta
Classifier: Topic :: Scientific/Engineering
Classifier: Programming Language :: Python :: 2.7
Classifier: Programming Language :: Python :: 3.4
Classifier: Programming Language :: Python :: 3.5
Classifier: Programming Language :: Python :: 3.6
Requires-Dist: numpy
Requires-Dist: scipy
Requires-Dist: h5py
